<?xml version="1.0" encoding="UTF-8"?>
<Transaction xmlns="http://euipo.europa.eu/trademark/data" xmlns:xsi="http://www.w3.org/2001/XMLSchema-instance" xsi:schemaLocation="http://euipo.europa.eu/trademark/data http://euipo.europa.eu/schemas/trademark/EM-TM-TradeMark-V3-4.xsd">
<TransactionHeader>
		<SenderDetails>
			<RequestProducerDateTime>2020-09-15T09:20:09</RequestProducerDateTime>
		</SenderDetails>
	</TransactionHeader>
<TradeMarkTransactionBody>
<TransactionContentDetails>
<TransactionIdentifier>018222481</TransactionIdentifier>
<TransactionCode>EM-Trade Mark</TransactionCode>
<TransactionData>
<TradeMarkDetails>
<TradeMark operationCode="Insert">
<RegistrationOfficeCode>EM</RegistrationOfficeCode>
<ApplicationNumber>018222481</ApplicationNumber>
<ApplicationDate>2020-04-08</ApplicationDate>
<RegistrationDate>2020-09-11</RegistrationDate>
<ApplicationLanguageCode>en</ApplicationLanguageCode>
<SecondLanguageCode>es</SecondLanguageCode>
<ExpiryDate>2030-04-08</ExpiryDate>
<MarkCurrentStatusCode milestone="23" status="1">Registered</MarkCurrentStatusCode>
<MarkCurrentStatusDate>2020-09-15</MarkCurrentStatusDate>
<KindMark>Individual</KindMark>
<MarkFeature>Figurative</MarkFeature>
<TradeDistinctivenessIndicator>false</TradeDistinctivenessIndicator>
<WordMarkSpecification>
<MarkVerbalElementText>Clylmedical</MarkVerbalElementText>
</WordMarkSpecification>
<MarkImageDetails>
<MarkImage>
<MarkImageIdentifier identifierKindCode="EM">000162189063</MarkImageIdentifier>
<MarkImageFileFormat>JPG</MarkImageFileFormat>
<MarkImageURI>file://018/222/018222481/000162189063.JPG</MarkImageURI>
<MarkImageCategory>
         <CategoryCodeDetails>
          <CategoryCode>26.02.05</CategoryCode>
          <CategoryCode>26.99.03</CategoryCode>
          <CategoryCode>26.99.12</CategoryCode>
          <CategoryCode>26.99.21</CategoryCode>
         </CategoryCodeDetails>
        </MarkImageCategory>
</MarkImage>
</MarkImageDetails>
<GoodsServicesDetails>
<GoodsServices>
 <ClassificationVersion/>
 <ClassDescriptionDetails>
  <ClassDescription>
   <ClassNumber>10</ClassNumber>
   <GoodsServicesDescription languageCode="bg">Защитни ръкавици за медицински цели; Хирургическо облекло; Медицински престилки; Хирургически костюми; Нощници за преглед на пациенти; Санитарни маски за медицински цели; Хирургически маски; Анестезиологични маски; Маски за дишане за медицинска употреба; Маски за медицински персонал; Респираторни маски за изкуствено дишане; Санитарни маски за медицински цели; Санитарни маски за предпазване от гъбички/плесен; Санитарни маски за предпазване от микроби и бацили; Санитарни маски за предпазване от полен; Санитарни маски за предпазване от вируси; Санитарни маски за изолиране от прах за медицински цели; Санитарни маски за предпазване от прах за медицински цели; Колани за пристягане на корема [за медицински цели]; Коремни корсети; Меки подложки за пристягане на корема; Подложки за акупресура; Ортопедични стелки за цели и половинка обувки; Ортопедични корсети за гръб за медицински цели; Скоби за крайници и свръзки за медицинска употреба; Протектори за лакти против епикондилитис; Шини за пръсти; Шиновидни материали за медицинска употреба; Пристягащи облекла; Медицински чанти за медицински инструменти; Апарати за моксотерапия; Ортопедична апаратура и инструменти за диагностична терапевтична употреба; Колани за ортопедични цели; Ортопедични уреди; Хирургически инструменти за употреба в ортопедична хирургия; Ортопедични обувки; Ортопедични поддържащи превръзки; Ортопедични подложки; Ортопедични стелки за обувки; Устройства за задна гръбначна фиксация за корекция на проблеми в гърба; Изкуствени крайници; Медицински подпори за тялото; Шини за китки, за медицински цели; Шини за глезени за медицински цели; Гръбначни ортопедични апарати; Хирургически апарати и инструменти; Съоръжения и медицински изделия за ортопедична хирургия; Апарати за физически упражнения за медицински цели; Бандажи [еластични].</GoodsServicesDescription>
   <GoodsServicesDescription languageCode="cs">Ochranné rukavice pro lékařské účely; Chirurgické oděvy; Lékařské pláště; Operační pláště; Pláště pro vyšetřování pacientů; Hygienické masky pro lékařské účely; Chirurgické masky; Anesteziologické masky; Respirační masky k lékařskému použití; Roušky pro lékařský personál; Respirační masky pro umělé dýchání; Hygienické masky pro lékařské účely; Sanitární masky pro účely izolace hub; Hygienické roušky pro účely izolace zárodků; Sanitární masky pro účely izolace pylu; Hygienické roušky k účelům izolace virů; Hygienické masky na ochranu před prachem pro lékařské účely; Hygienické masky na ochranu před prachem pro lékařské účely; Břišní pásy (k léčebným účelům); Břišní korzety; Břišní podložky; Akupresurní podložky; Ortopedické vložky do obuvi; Ortézy a bandáže zad pro lékařské účely; Výztuhy pro končetiny a klouby pro léčebné použití; Chrániče loktů při zánětu epikondylu; Dlahy na prsty; Dlahové materiály k lékařskému použití; Kompresní oděvy; Lékařské vaky určené pro ukládání lékařských nástrojů; Přístroje a zařízení na moxování; Ortopedické přístroje a nástroje pro diagnostické a terapeutické použití; Ortopedické pásy; Ortopedické přístroje; Chirurgické nástroje k použití při ortopedické chirurgii; Ortopedická obuv; Ortopedické podpůrné bandáže; Ortopedické pomůcky; Protetické vložky do obuvi; Zařízení na posteriorní fixaci páteře pro napravení defektů zad; Umělé končetiny; Lékařské podpory a výztuže na tělo; Podpěry zápěstí pro lékařské použití; Podpěry kotníku pro lékařské účely; Vertebrální ortopedické přístroje; Chirurgické přístroje a nástroje; Lékařská zařízení a nástroje pro ortopedickou chirurgii; Přístroje na tělesná cvičení pro lékařské účely; Obvazy [elastické].</GoodsServicesDescription>
   <GoodsServicesDescription languageCode="da">Beskyttelseshandsker til medicinske formål; Operationsdragter; Medicinske operationskitler; Operationskitler; Patientundersøgelseskitler; Sanitære masker til medicinske formål; Operationsmasker; Bedøvelsesmasker; Åndedrætsværn til medicinske formål; Masker til brug for medicinsk personel; Respirationsmasker til kunstig respiration; Beskyttelsesmasker til medicinske formål; Hygiejnemasker til isolering mod svampe; Hygiejniske masker til isolering af mikrober; Hygiejnemasker til isolering mod pollen; Hygiejnemasker til virusisoleringsformål; Sanitære støvisoleringsmasker til medicinske formål; Sanitære masker til beskyttelse mod støv til medicinske formål; Underlivsbælter til medicinske formål; Underlivskorsetter; Underlivsbandager; Akupressurmåtter; Svangstøtter til fodtøj; Rygstøtter til medicinske formål; Støtter til lemmer og led til medicinske formål; Albuebeskyttere mod tennisalbue; Fingerskinner; Skinnematerialer til medicinske formål; Kompressionsbeklædning; Tasker til medicinske instrumenter; Apparater til moxibustion; Ortopædiske apparater og instrumenter til diagnostiske og terapeutiske formål; Ortopædiske bælter; Ortopædiske apparater; Kirurgiske instrumenter til brug ved ortopædkirurgi; Ortopædiske sko; Ortopædiske støttebandager; Ortopædiske bøjler; Orthotiske indlæg til fodtøj; Anordninger til fiksering af nedre del af rygraden i forbindelse med korrigering af ryglidelser; Kunstige lemmer; Medicinske støttebandager; Håndledsbind til medicinske formål; Ankelstøtter til medicinske formål; Ortopædiske apparater til rygsøjlen; Kirurgiske apparater og instrumenter; Medicinske enheder og instrumenter til ortopædkirurgi; Apparater til fysisk træning, medicinske formål; Bandager, elastiske.</GoodsServicesDescription>
   <GoodsServicesDescription languageCode="de">Schutzhandschuhe für medizinische Zwecke; Operationsbekleidung; Medizinische Kittel; Operationskittel; Patientenuntersuchungshemden; Mundschutz für medizinische Zwecke; Chirurgischer Mundschutz; Narkosemasken; Atemmasken für medizinische Zwecke; Masken für medizinisches Personal; Atemmasken für künstliche Beatmung; Hygienemasken für medizinische Zwecke; Hygienemasken zur Pilzisolierung; Hygienemasken zur Keimisolierung; Hygienemasken zur Pollenisolierung; Hygienemasken zur Virusisolierung; Hygienemasken zur Staubabsonderung für medizinische Zwecke; Hygienemasken zum Schutz vor Staub für medizinische Zwecke; Leibbinden [für medizinische Zwecke]; Leibhalter; Unterleibspelotten; Akupressurmatten; Orthopädische Einlagen für Schuhe; Rückenstützen für medizinische Zwecke; Klammern für Gliedmaßen und Gelenke für den medizinischen Gebrauch; Ellbogenschützer für Epicondylitis; Fingerschienen; Schienen für medizinische Zwecke; Kompressionsbekleidung; Medizinische Beutel zum Halten von medizinischen Instrumenten; Moxibustionsapparate; Orthopädische Apparate und Instrumente für diagnostische und therapeutische Zwecke; Gürtel, orthopädische; Orthopädiegeräte; Chirurgische Instrumente für die orthopädische Chirurgie; Orthopädische Schuhe; Orthopädische Stützbandagen; Orthopädische Stützen; Orthetische Einlagen für Schuhwaren; Vorrichtungen zur Rückenwirbelsäulenfixierung für die Korrektur von Rückenfehlhaltungen; Prothesen; Medizinische Stützen für den Körper; Handgelenkstützen für medizinische Zwecke; Knöchelstützen für medizinische Zwecke; Orthopädische Geräte für die Wirbelsäule; Chirurgische Apparate und Instrumente; Ärztliche Vorrichtungen und Instrumente für die orthopädische Chirurgie; Medizinische Geräte für Körperübungen und Krankengymnastik; Elastische Bandagen.</GoodsServicesDescription>
   <GoodsServicesDescription languageCode="el">Προστατευτικά γάντια για ιατρική χρήση· Χειρουργικές στολές· Ιατρικές ρόμπες· Χειρουργικές ποδιές· Ρόμπες εξέτασης ασθενών· Μάσκες υγιεινής για ιατρική χρήση· Χειρουργικές μάσκες· Αναισθητικές μάσκες· Αναπνευστικές μάσκες για ιατρικές χρήσεις· Μάσκες για το ιατρικό προσωπικό· Αναπνευστικές μάσκες για τεχνητή αναπνοή· Μάσκες υγιεινής για ιατρική χρήση· Μάσκες υγιεινής για σκοπούς απομόνωσης μυκήτων· Μάσκες υγιεινής για απομόνωση μικροβίων· Μάσκες υγιεινής για σκοπούς απομόνωσης γύρης· Μάσκες υγιεινής για απομόνωση ιών· Μάσκες υγιεινής για την απομόνωση της σκόνης προοριζόμενες για ιατρική χρήση· Μάσκες υγιεινής για παρεμπόδιση της σκόνης για ιατρική χρήση· Κοιλιακές ζώνες [για ιατρικούς σκοπούς]· Κοιλιακοί κοιλεπίδεσμοι· Επιθέματα υπογάστρια· Υποθέματα για πιεσοθεραπεία (χειρομαλάξεις μέσω άσκησης δακτυλικής πίεσης)· Στηρίγματα της καμάρας του ποδιού για υποδήματα· Στηρίγματα πλάτης για ιατρική χρήση· Διατάξεις στήριξης για μέλη και αρθρώσεις για ιατρική χρήση· Προστατευτικά αγκώνα για επικονδυλίτιδα· Νάρθηκες δακτύλων· Υλικά ναρθικοποίησης για ιατρική χρήση· Ενδύματα συμπίεσης· Ιατρικές τσάντες σχεδιασμένες για ιατρικά εργαλεία· Συσκευές για καύση μόξας· Ορθοπαιδικές συσκευές και εργαλεία για διαγνωστική και θεραπευτική χρήση· Ζώνες για ορθοπαιδική χρήση· Ορθοπεδικές συσκευές· Χειρουργικά όργανα για χρήση στην ορθοπεδική χειρουργική· Ορθοπαιδικά παπούτσια· Ορθοπεδικοί επίδεσμοι στήριξης· Ορθοπεδικά υποστηρίγματα· Ορθοπεδικά ενθέματα για υποδήματα· Διατάξεις οπίσθιας στερέωσης σπονδυλικής στήλης για τη διόρθωση ανωμαλιών της ράχης· Μέλη τεχνητά· Ιατρικά στηρίγματα σώματος· Στηρίγματα καρπών για ιατρική χρήση· Επίδεσμοι αστραγάλων για ιατρική χρήση· Σπονδυλικές ορθοπεδικές συσκευές· Χειρουργικές συσκευές και όργανα· Ιατρικές διατάξεις και εργαλεία ορθοπαιδικής χειρουργικής· Ιατρικές συσκευές για σωματική άσκηση· Επίδεσμοι ελαστικοί.</GoodsServicesDescription>
   <GoodsServicesDescription languageCode="en">Protective gloves for medical use; Surgical scrub suits; Medical gowns; Surgical gowns; Patient examination gowns; Sanitary masks for medical purposes; Surgical masks; Anaesthetic masks; Respiratory masks for medical purposes; Masks for use by medical personnel; Respiratory masks for artificial respiration; Sanitary masks for medical use; Sanitary masks for fungus isolation purposes; Sanitary masks for germ isolation purposes; Sanitary masks for pollen isolation purposes; Sanitary masks for virus isolation purposes; Sanitary masks for dust isolation for medical purposes; Sanitary masks for dust prevention for medical purposes; Abdominal belts [for medical purposes]; Abdominal corsets; Abdominal pads; Acupressure mats; Arch supports for boots and shoes; Back supports for medical purposes; Braces for limbs and joints, for medical use; Elbow guard for epicondylitis; Finger splints; Splints for medical purposes; Compression garments; Medical bags designed to hold medical instruments; Moxibustion apparatus; Orthopedic apparatus and instruments for diagnostic and therapeutic use; Orthopedic belts; Orthopedic apparatus; Surgical instruments for use in orthopedic surgery; Orthopedic shoes; Orthopedic support bandages; Orthopedic supports; Orthopaedic inserts for footwear; Posterior spinal fixation devices for the correction of back defects; Artificial limbs; Medical supports for the body; Wrist supports for medical use; Ankle supports for medical use; Vertebral orthopedic apparatus; Surgical apparatus and instruments; Medical apparatus and instruments for orthopedic surgery; Physical exercise apparatus for medical purposes; Bandages, elastic.</GoodsServicesDescription>
   <GoodsServicesDescription languageCode="es">Guantes de protección para uso médico; Trajes quirúrgicos; Batas médicas; Batas para uso quirúrgico; Batas sanitarias para la examinación de pacientes; Mascarillas sanitarias para uso médico; Mascarillas quirúrgicas; Mascarillas de anestesia; Mascarillas respiratorias para uso médico; Mascarillas para personal médico; Mascarillas respiratorias para la respiración artificial; Mascarillas sanitarias para uso médico; Mascarillas sanitarias para el aislamiento de hongos; Mascarillas sanitarias de aislamiento de gérmenes; Mascarillas sanitarias para el aislamiento del polen; Mascarillas sanitarias para el aislamiento vírico; Mascarillas sanitarias para aislar del polvo con fines médicos; Mascarillas sanitarias para prevenir el polvo con fines médicos; Cinturones abdominales [para uso médico]; Fajas abdominales; Almohadillas abdominales; Esteras de acupresión; Soportes de arco para calzado; Almohadillas dorsales para uso médico; Férulas para miembros y articulaciones para uso médico; Coderas para epicondilitis; Férulas para dedos; Materiales de entablillado para uso médico; Prendas de compresión; Bolsas de uso médico diseñadas para contener instrumental médico; Aparatos para la moxibustión; Aparatos e instrumentos ortopédicos para diagnósticos y para uso terapéutico; Correas con una finalidad ortopédica; Aparatos ortopédicos; Instrumentos quirúrgicos para cirugía ortopédica; Zapatos ortopédicos; Vendajes ortopédicos de sujeción; Soportes ortopédicos; Refuerzos ortopédicos para insertar en el calzado; Dispositivos de fijación posterior en la columna vertebral para la corrección de defectos de la espalda; Miembros artificiales; Soportes médicos para el cuerpo; Soportes de muñeca para uso médico; Tobilleras [soportes] para uso médico; Aparatos ortopédicos vertebrales; Aparatos e instrumentos quirúrgicos; Dispositivos e instrumentos médicos para la cirugía ortopédica; Aparatos de ejercicio físico para uso médico; Vendas elásticas.</GoodsServicesDescription>
   <GoodsServicesDescription languageCode="et">Meditsiinilised kaitsekindad; Kirurgilised operatsioonikitlid; Meditsiinilised kitlid; Kirurgias kasutatavad kitlid; Kitlid patsiendi läbivaatuseks; Meditsiinilised hügieenilised maskid; Kirurgimaskid; Anesteesiamaskid; Meditsiinilised hingamismaskid; Maskid meditsiinipersonalile; Kunstliku hingamise respiraatormaskid; Meditsiinilised hügieenimaskid; Seente eest kaitsvad hügieenilised maskid; Pisikute eest kaitsvad hügieenilised maskid; Õietolmu eest kaitsvad hügieenilised maskid; Viiruste eest kaitsvad hügieenilised maskid; Meditsiinilised tolmukaitsemaskid hügieenivahendina; Tolmumaskid meditsiinis kasutamiseks; Kõhuvööd (meditsiinilised); Kõhukorsetid; Kõhupadjad; Punktimassaažimatid; Jalatsite tallatoed; Meditsiinilised seljatoed; Jäseme- ja liigeseravisidemed; Epikondüliidi tugikaitsmed; Sõrmelahased; Meditsiinis kasutatavad lahasematerjalid; Surverõivad; Meditsiinilised kotid meditsiiniinstrumentide hoidmiseks; Moksibustsiooniseadmed; Ortopeedilised seadmed ja instrumendid diagnostiliseks ja terapeutiliseks kasutuseks; Ortopeedilised vööd; Ortopeediaseadmed; Ortopeedilises kirurgias kasutatavad kirurgiariistad; Ortopeedilised kingad; Ortopeedilised tugibandaažid; Ortopeedilised toed; Ortootilised jalanõude sisetallad; Posterioorsed spinaalse kinnituse vahendid seljadefektide korrigeerimiseks; Kunstjäsemed, tehisjäsemed, jäsemeproteesid; Meditsiinilised toed kehale; Meditsiinilised randmetoed; Meditsiinilised pahkluutoed; Lülisamba ortopeedilised seadmed; Kirurgiaseadmed ja -riistad; Ortopeediliseks kirurgia meditsiiniseadmed ja -riistad; Meditsiinilised võimlemisseadmed; Elastiksidemed.</GoodsServicesDescription>
   <GoodsServicesDescription languageCode="fi">Suojakäsineet lääketieteellisiin tarkoituksiin; Pesupuvut kirurgeille; Leikkaussalivaatteet; Leikkaussalivaatteet kirurgiseen käyttöön; Potilaantutkimusvaatteet; Saniteettinaamarit lääketieteellisiin tarkoituksiin; Kirurgin naamarit; Anesteettiset maskit; Hengitysnaamarit lääkinnällisiin tarkoituksiin; Suojanaamarit lääkintähenkilökuntaa varten; Hengitysnaamarit tekohengitykseen; Saniteettinaamarit lääketieteellisiin tarkoituksiin; Hygienianaamarit sieniltä suojautumiseen; Hygienianaamarit bakteereilta suojautumistarkoituksiin; Hygienianaamarit siitepölyltä suojautumiseen; Hygienianaamarit viruksilta suojautumiseen; Saniteettimaskit pölyn eristämiseen lääkinnällisiin tarkoituksiin; Hygieniamaskit pölyltä suojautumiseen lääketieteellisiin tarkoituksiin; Vatsavyöt [lääketieteellisiin tarkoituksiin]; Pallealiivit; Palleatyynyt; Piikkimatot akupainantaan; Jalkineiden kaarituet; Selkätuet lääketieteellisiin tarkoituksiin; Jäsenille ja nivelille tarkoitetut tuet lääketieteelliseen käyttöön; Kyynärpääsuojukset epikondyliittiä varten; Sormilastat; Lastat lääketieteellisiin tarkoituksiin; Kompressiovaatteet; Lääketieteelliset laukut lääketieteellisten välineiden säilyttämiseen; Ihon polttohoitolaitteet; Ortopediset laitteet ja välineet diagnostiseen ja terapeuttiseen käyttöön; Vyöt ortopedisiin tarkoituksiin; Ortopediavälineet; Kirurgiset välineet käytettäväksi ortopedisessa kirurgiassa; Ortopediset jalkineet; Ortopediset tukisiteet; Ortopediset tuet; Ortopediset jalkinetarvikkeet; Taakse asennettavat selkärangan kiinnityslaitteet selkävikojen korjaamiseen; Tekojäsenet; Lääkinnälliset vartalotuet; Rannetuet lääketieteelliseen käyttöön; Nilkkatuet lääketieteelliseen käyttöön; Nikamille tarkoitetut ortopediset laitteet; Kirurgiset laitteet ja välineet; Lääketieteelliset laitteet ja välineet ortopediseen kirurgiaan; Kuntoiluvälineet lääketieteellisiin tarkoituksiin; Siteet [elastiset].</GoodsServicesDescription>
   <GoodsServicesDescription languageCode="fr">Gants protecteurs à usage médical; Tenues chirurgicales stériles; Blouses à usage médical; Blouses chirurgicales; Blouses d'examen pour patients; Masques hygiéniques à usage médical; Masques chirurgicaux; Masques d'anesthésie; Masques respiratoires à usage médical; Masques utilisés par le personnel médical; Masques respiratoires pour la respiration artificielle; Masques hygiéniques à usage médical; Masques sanitaires à des fins d'isolation fongique; Masques hygiéniques pour l'isolation de germes; Masques sanitaires à des fins d'isolation au pollen; Masques hygiéniques à des fins d'isolation virale; Masques hygiéniques de protection contre la poussière à usage médical; Masques hygiéniques antipoussières à usage médical; Ceintures abdominales à usage médical; Corsets abdominaux; Compresses abdominales; Tapis d'acupression; Soutiens de voûtes plantaires pour chaussures; Supports dorsaux à usage médical; Appareils orthopédiques à usage médical pour membres et articulations; Coudière pour le traitement de l'épicondylite; Attelles pour doigts; Matériaux de contention à usage médical; Vêtements de compression; Sacs médicaux destinés à contenir des instruments médicaux; Appareils de moxibustion; Appareils et instruments orthopédiques à usage diagnostique et thérapeutique; Sangles à usage orthopédique; Appareils orthopédiques; Instruments chirurgicaux destinés à la chirurgie orthopédique; Chaussures orthopédiques; Bandages de maintien orthopédiques; Supports orthopédiques; Orthèses à insérer dans les chaussures; Dispositifs de fixation rachidienne par voie postérieure pour la correction d'anomalies dorsales; Prothèses; Dispositifs médicaux de soutien du corps; Supports pour poignets à usage médical; Supports de cheville à usage médical; Appareils orthopédiques vertébraux; Appareils et instruments chirurgicaux; dispositifs et instruments médicaux pour la chirurgie orthopédique; Appareils médicaux pour exercices corporels; Bandages élastiques.</GoodsServicesDescription>
   <GoodsServicesDescription languageCode="hr">Zaštitne rukavice za medicinske svrhe; Kirurška odijela; Medicinske kute; Kirurški ogrtači; Košulje za pregled, za pacijente; Sanitarne maske za medicinske svrhe; Kirurške maske; Maske za anesteziju; Maske za disanje za medicinske namjene; Maske za medicinsko osoblje; Respiracijske maske za umjetno disanje; Sanitarne maske za medicinske svrhe; Sanitarne maske za potrebe izolacije gljivica; Sanitarne maske za potrebe zaštite od klica; Sanitarne maske za potrebe izolacije peludi; Sanitarne maske za potrebe izolacije virusa; Sanitarne maske za izolaciju prašine za medicinske potrebe; Sanitarne maske za sprečavanje udisanja prašine za medicinske potrebe; Trbušni pojasevi [za medicinske svrhe]; Trbušni [abdominalni] steznici; Jastučići za donji trbuh; Prostirke za akupresuru; Ulošci za obuću; Potpore za leđa za medicinske svrhe; Ortoze za udove i zglobove za medicinsku uporabu; Štitnici za laktove za epikondilitis; Udlage za prste; Imobilizacijski materijali za medicinsku uporabu; Kompresijska odjeća; Medicinske torbe za držanje medicinskih instrumenata; Aparati za moksibuciju [kinesku metodu liječenja toplinom vatre]; Ortopedski uređaji i instrumenti za dijagnostičku i terapijsku uporabu; Remeni za ortopedske svrhe; Ortopedski aparati; Kirurški instrumenti za uporabu pri ortopedskim operacijama; Ortopedske cipele; Ortopedske potporne bandaže; Ortopedski steznici; Ortotički umeci za obuću; Uređaji za fiksaciju posteriorna dijela kralježnice za ispravljanje leđnih deformacija; Proteze [umjetni udovi]; Medicinski podupirači za tijelo; Potpore za zapešće za medicinsku uporabu; Steznici za zglobove za medicinske svrhe; Vertebralni ortopedski uređaji; Kirurški aparati i instrumenti; Medicinski uređaji i instrumenti za otropedsku kirurgiju; Uređaji za vježbe za medicinske potrebe; Elastični zavoji.</GoodsServicesDescription>
   <GoodsServicesDescription languageCode="hu">Védőkesztyűk gyógyászati használatra; Sebészeti ruhák, műtős ruhák; Orvosi köpenyek; Köpenyek sebészeti használatra; Betegvizsgáló köpenyek; Gyógyászati célú egészségügyi maszkok; Sebészeti maszkok; Altató maszkok; Légzőmaszkok orvosi célokra; Maszkok egészségügyi személyzet általi használatra; Légzőmaszkok mesterséges lélegeztetéshez; Gyógyászati célú egészségügyi maszkok; Egészségügyi maszkok gomba izolálására; Egészségügyi maszkok a sejtmagok szétválasztásához; Egészségügyi maszkok pollen izolálására; Egészségügyi maszkok vírusizolációs célokra; Egészségügyi maszkok porizolációhoz gyógyászati célokra; Egészségügyi maszkok por elleni védelemre, orvosi célokra; Haskötők [orvosi használatra]; Hasfűzők; Hasi kötések; Akupresszúrás szőnyegek; Lúdtalpbetétek lábbelikhez; Háttámaszok gyógyászati célokra; Merevítők végtagokhoz és ízületekhez, gyógyászati használatra; Könyökvédők teniszkönyök kezelésére; Ujjsínek; Rögzítőanyagok, sínek gyógyászati használatra; Kompressziós ruhák; Orvosi műszerek tárolására tervezett orvosi táskák; Készülékek moxakezeléshez; Ortopéd berendezések és eszközök diagnosztikai és terápiás használatra; Övek ortopédiai célokra; Ortopédiai eszközök; Ortopéd sebészetben használatos sebészeti eszközök; Ortopédiai lábbelik; Ortopédiai támasztókötések; Ortopédiai tartók; Ortopédiai betétek lábbelikhez; Hátsó gerincrögzítő eszközök háthibák korrigálására; Művégtagok; Orvosi testtámaszok; Csuklószorítók gyógyászati használatra; Orvosi bokarögzítők; Gerinc ortopédiai berendezések; Sebészeti készülékek és eszközök; Orvosi eszközök és műszerek ortopédiai sebészethez; Testmozgásra szolgáló gyógyászati eszközök, készülékek; Rugalmas kötszerek.</GoodsServicesDescription>
   <GoodsServicesDescription languageCode="it">Guanti di protezione per uso medico; Camici chirurgici; Camici medici; Camici da chirurgo; Camici da esame per pazienti; Maschere igieniche per uso medico; Mascherine chirurgiche; Maschere anestetiche; Maschere respiratorie per uso medico; Maschere utilizzate dal personale medico; Maschere respiratorie per la respirazione artificiale; Maschere igieniche per uso medico; Maschere sanitarie per l'isolamento di funghi; Maschere igieniche per l'isolamento di germi; Maschere sanitarie per l'isolamento di polline; Maschere igieniche per l'isolamento di virus; Maschere igieniche per l'isolamento delle polveri, per uso medico; Maschere igieniche per la protezione dalla polvere per uso medico; Fasce addominali [per uso medico]; Corsetti addominali; Compresse ipogastriche; Tappetini per acupressione; Plantari per calzature; Busti per uso medico; Supporti per membra e articolazioni per uso medico; Paragomiti per epicondilite; Stecche per le dita; Materiale per stecche per uso medico; Indumenti di compressione; Borse mediche destinate a contenere strumenti medici; Apparecchi per moxibustione; Apparecchi e strumenti ortopedici per uso diagnostico e terapeutico; Cinghie per uso ortopedico; Apparecchi ortopedici; Strumenti chirurgici per la chirurgia ortopedica; Scarpe ortopediche; Fasciature di supporto ortopediche; Supporti ortopedici; Inserti ortopedici per calzature; Dispositivi per fissaggio spinale posteriore per la correzione di difetti della schiena; Arti artificiali; Dispositivi medici per sostenere il corpo; Supporti da polso per uso medico; Supporti per caviglia per uso medico; Apparecchi ortopedici vertebrali; Apparecchi e strumenti chirurgici; Dispositivi e strumenti medici per la chirurgia ortopedica; Apparecchi per esercizi fisici per scopi medici; Fasciature elastiche.</GoodsServicesDescription>
   <GoodsServicesDescription languageCode="lt">Apsauginės pirštinės medicinos reikmėms; Chirurginiai kostiumai [operaciniai]; Medicininiai chalatai; Chalatai chirurgijos reikmėms; Pacientų apžiūros chalatai; Sanitarinės kaukės medicinos reikmėms; Chirurginės kaukės; Anestezijos (nejautros) kaukės; Kvėpavimo kaukės medicinos reikmėms; Kaukės medicinos personalui; Respiratorių kaukės (dirbtinio kvėpavimo reikmėms); Sanitarinės kaukės medicinos reikmėms; Sanitarinės kaukės grybelių izoliacijai; Sanitarinės kaukės, skirtos gemalų izoliavimo reikmėms; Žiedadulkių izoliacijos kaukės; Sanitarinės kaukės virusų išskyrimo reikmėms; Sanitarinės kaukės nuo dulkių medicinos reikmėms; Sanitarinės nuo dulkių apsaugančios kaukės medicinos reikmėms; Pilvo diržai [medicinos reikmėms]; Pilvo korsetai; Pilvo pagalvėlės; Akupresūros kilimėliai; Ortopediniai vidpadžiai; Nugaros atramos medicinos reikmėms; Įtvarai galūnėms ir sąnariams medicinos reikmėms; Antalkūniai nuo epikondilito; Pirštų įtvarai; Medicininės įtveriamosios medžiagos; Kompresiniai drabužiai; Medicininiai krepšeliai medicinos instrumentams laikyti; Moksibustijos aparatai; Ortopedijos aparatai ir prietaisai, skirti diagnostiniams ir terapeutiniams tyrimams; Ortopediniai diržai; Ortopedijos prietaisai; Chirurginiai instrumentai ortopedinės chirurgijos reikmėms; Ortopediniai batai; Ortopediniai palaikantys tvarsčiai; Ortopedinės atramos; Ortopediniai avalynės įdėklai; Užpakalinės stuburo dalies fiksacijos įtaisai nugaros defektams koreguoti; Kojų ir rankų protezai; Medicininės kūno atramos; Riešo atramos (medicinos reikmėms); Kulkšnių įtvarai medicinos reikmėms; Stuburo ortopediniai aparatai; Chirurginiai aparatai ir instrumentai; Ortopedinės chirurgijos medicininiai prietaisai ir instrumentai; Fizinių pratimų aparatai (medicinos reikmėms); Tvarsčiai [elastiniai].</GoodsServicesDescription>
   <GoodsServicesDescription languageCode="lv">Aizsargcimdi medicīniskiem nolūkiem; Ķirurģisko operāciju personāla apģērbs; Medicīniskais apģērbs; Halāti ķirurģiskiem nolūkiem; Pacienta izmeklēšanai paredzētie tērpi; Sanitārās maskas medicīniskiem nolūkiem; Ķirurģiskās maskas; Anestēzijas maskas; Elpošanas maskas medicīniskiem nolūkiem; Medicīnas personālam paredzētās maskas; Respiratoru maskas, kas paredzētas mākslīgajai elpināšanai; Sanitārās maskas medicīniskiem nolūkiem; Sejas aizsargmaskas sēnīšu infekcijas izolācijas vajadzībām; Higiēniskās maskas mikrobu izolēšanas nolūkiem; Sanitārās aizsargmaskas ziedputekšņu izolācijas vajadzībām; Higiēniskās maskas vīrusu izolēšanas nolūkiem; Sanitārās maskas putekļu izolācijai medicīniskiem nolūkiem; Sanitārās maskas aizsardzībai pret putekļiem medicīniskiem nolūkiem; Vēdera jostas (medicīniskiem nolūkiem); Vēdera korsetes; Vēdera polsteri; Akupresūras paklājiņi; Atbalsti pēdas velvei apavos; Muguras balsti medicīniskiem nolūkiem; Locekļu un locītavu saites izmantošanai medicīnā; Elkoņu aizsargi epikondilīta gadījumos; Šinas roku pirkstiem; Iešinēšanas materiāli medicīniskiem nolūkiem; Kompresijas apģērbs; Medicīniskās somas, kas izgatavotas medicīnisko instrumentu glabāšanai; Moksa terapijas aparāti; Ortopēdiskās iekārtas un instrumenti, kas ir paredzēti diagnostikas un terapeitiskiem nolūkiem; Ortopēdiskās jostas; Ortopēdijas ierīces; Ķirurģiski instrumenti, kas paredzēti lietošanai ortopēdiskajā ķirurģijā; Ortopēdiskie apavi; Ortopēdiskie atbalsta pārsēji (bandāžas); Ortopēdiskie atbalsti; Ortopēdiskie ieliktņi apaviem; Apakšējās mugurkaula fiksācijas ierīces muguras defektu labošanai; Locekļu protēzes; Medicīniskie ķermeņa atbalsti; Plaukstas locītavas atbalsti, kas paredzēti izmantošanai medicīnā; Potītes ortozes medicīniskiem nolūkiem; Vertebrālā ortopēdiskā aparatūra; Ķirurģiskās ierīces un instrumenti; Medicīnas ierīces un instrumenti ortopēdiskajai ķirurģijai; Fizisko vingrinājumu aparāti medicīniskiem nolūkiem; Elastīgie pārsēji.</GoodsServicesDescription>
   <GoodsServicesDescription languageCode="mt">Ingwanti protettivi għal skopijiet mediċi; Ilbies għall-kirurgi; Ġagagi mediċi; Ġagagi għall-użu kirurġiku; Ġagagi għall-eżaminazzjoni ta' pazjenti; Maskri sanitarji għal skopijiet mediċi; Maskri kirurġiċi; Maskri tal-loppju; Maskri respiratorji għal skopijiet mediċi; Maskri għal personal mediku; Maskri respiratorji għan-nifs artifiċjali; Maskri sanitarji għal skopijiet mediċi; Maskri sanitarji għal skopijiet ta' iżolament tal-fungus; Maskri sanitarji għal skopijiet ta' iżolament ta' mikrobi; Maskri sanitarji għal skopijiet ta' iżolament tal-polline; Maskri sanitarji għal skopijiet ta' iżolament tal-virus; Maskri sanitarji għall-iżolament tat-trab għal skopijiet mediċi; Maskri sanitarji għall-prevenzjoni mit-trab għal skopijiet mediċi; Ċinturini taż-żaqq [għal skopijiet mediċi]; Kriepet addominali; Kuxxinetti addominali; Twapet żgħar tal-agupressa; Appoġġ għall-vojt tas-saqajn fiż-żraben; Appoġġ tad-dahar għal skopijiet mediċi; Ċineg għar-riġlejn u għall-ġogi għall-użu mediku; Ilqugħ għall-minkeb għall-epikondilalġija; Qassaba tas-swaba'; Materjali tal-qassaba għall-użu mediku; Ilbies tal-kompressjoni; Boroż mediċi għaż-żamma tal-istrumenti mediċi; Apparat għall-kura bil-ħruq tal-moksa; Apparat u strumenti ortopediċi għall-użu dijanjostiku u terapewtiku; Ċinturini għal skopijiet ortopediċi; Tagħmir ortopediku; Strumenti kirurġiċi għall-użu fil-kirurġija ortopedika; Żraben ortopediċi; Faxxaturi tas-sapport ortopediċi; Appoġġi ortopediċi; Suletti ortotiċi għaż-żraben; Tagħmir għall-iffissar spinali posterjuri għall-korezzjoni ta' difetti fid-dahar; Dirgħajn artifiċjali; Supporti mediċi għall-ġisem; Appoġġi tal-polz għall-użu mediku; Partijiet tal-appoġġ ta' għakset is-sieq għall-użu mediku; Apparat ortopediku vertebrali; Apparat u strumenti kirurġiċi; Tagħmir u strumenti mediċi għall-kirurġija ortopedika; Apparat għall-eżerċizzju fiżiku, għal skopijiet mediċi; Faxex, elastiċi.</GoodsServicesDescription>
   <GoodsServicesDescription languageCode="nl">Beschermende handschoenen voor medische doeleinden; Operatiepakken (voor chirurgisch gebruik); Schorten (Medische -); Operatieschorten; Onderzoeksschorten voor patiënten; Hygiënische maskers voor medische doeleinden; Gezichtsmaskers voor chirurgisch gebruik; Verdovingsmaskers; Ademhalingsmaskers voor medische doeleinden; Maskers te gebruiken door medisch personeel; Ademhalingsmaskers voor kunstmatige beademing; Hygiënische maskers voor medische doeleinden; Hygiënische maskers voor het isoleren van schimmels; Hygiënische maskers voor het isoleren van ziektekiemen; Hygiënische maskers voor het isoleren van pollen; Hygiënische maskers voor het isoleren van virussen; Hygiënische maskers voor stofisolatie voor medische doeleinden; Hygiënische maskers voor stofpreventie voor medische doeleinden; Gordels (buik -) [voor medisch gebruik]; Korsetten voor de onderbuik; Drukkussentjes voor de onderbuik; Acupressuurmatten; Steunzolen voor schoenen; Ruggensteunen voor medische doeleinden; Beugels voor ledematen en gewrichten, voor medisch gebruik; Beschermers voor tennisarmen; Spalken voor de vingers; Spalkmateriaal voor medisch gebruik; Compressiekleding; Medische tassen gemaakt voor het dragen van medische instrumenten; Moxibustie-toestellen; Orthopedische apparaten en instrumenten voor diagnostisch en therapeutisch gebruik; Riemen voor orthopedische doeleinden; Orthopedisch gerei; Chirurgische instrumenten voor gebruik in orthopedische chirurgie; Orthopedische schoenen; Orthopedische steunverbanden; Orthopedische steunen; Orthopedische inlegstukken voor schoeisel; Fixeren van de ruggenwervel voor het corrigeren van aandoeningen aan de rug (Toestellen voor het -); Kunstledematen; Medische steunen voor het lichaam; Polssteunen voor medisch gebruik; Enkelsteunen voor medische doeleinden; Orthopedische apparatuur voor de wervelkolom; Chirurgische apparaten en instrumenten; Medische hulpmiddelen en instrumenten voor orthopedische chirurgie; Medische apparatuur voor lichaamsoefeningen; Verbanden, elastisch.</GoodsServicesDescription>
   <GoodsServicesDescription languageCode="pl">Rękawiczki ochronne do celów medycznych; Chirurgiczna odzież operacyjna; Kitle; Fartuchy do użytku chirurgicznego; Fartuchy do badania pacjentów; Maski sanitarne do celów medycznych; Maski chirurgiczne; Maski anestezjologiczne; Maski oddechowe do celów medycznych; Maski stosowane przez personel medyczny; Maski do sztucznego oddychania; Maski higieniczne do celów medycznych; Maski higieniczne do celów izolacji przed grzybami; Maski higieniczne do celów izolacji przed zarazkami; Maski higieniczne do celów izolacji przed pyłkami; Maski higieniczne do celów izolacji przed wirusami; Maski higieniczne do osłony przed pyłem do celów medycznych; Maski sanitarne stosowane w celu ochrony przed kurzem do celów medycznych; Pasy brzuszne [do celów medycznych]; Gorsety brzuszne; Podkładki podbrzuszne; Maty do akupresury; Wkładki z podparciem łuku stopy do obuwia; Stabilizatory pleców do celów medycznych; Ochraniacze na kończyny i stawy do użytku medycznego; Ochraniacze na łokieć stosowane podczas zapalenia nadkłykcia; Szyny do palców; Materiały unieruchamiające do użytku medycznego; Odzież kompresyjna; Torby medyczne przeznaczone do przechowywania instrumentów medycznych; Urządzenia do ignipunktury; Ortopedyczne urządzenia i przyrządy do celów diagnostycznych i leczniczych; Pasy do celów ortopedycznych; Przyrządy ortopedyczne; Instrumenty chirurgiczne do użytku w chirurgii ortopedycznej; Obuwie ortopedyczne; Ortopedyczne bandaże usztywniające; Artykuły ortopedyczne; Ortopedyczne wkładki do obuwia; Urządzenia do mocowania do kręgosłupa służące do korygowania defektów pleców; Protezy kończyn; Medyczne środki podtrzymujące do ciała; Usztywniacze nadgarstka do użytku medycznego; Opaski uciskowe na kostkę do użytku medycznego; Aparatura ortopedyczna stosowana przy uszkodzeniach kręgów; Aparatura i instrumenty chirurgiczne; Przyrządy i instrumenty medyczne stosowane w chirurgii ortopedycznej; Urządzenia do ćwiczeń fizycznych do celów medycznych; Bandaże elastyczne.</GoodsServicesDescription>
   <GoodsServicesDescription languageCode="pt">Luvas de proteção para uso médico; Vestuário para cirurgia; Batas médicas; Batas para uso cirúrgico; Batas de observação de pacientes; Máscaras higiénicas para uso médico; Máscaras cirúrgicas; Máscaras anestésicas; Máscaras respiratórias para uso médico; Máscaras para pessoal médico; Máscaras para respiração artificial; Máscaras higiénicas para uso medicinal; Máscaras higiénicas para fins de isolamento contra fungos; Máscaras higiénicas para fins de isolamento de germes; Máscaras higiénicas para fins de isolamento contra pólenes; Máscaras higiénicas para fins de isolamento de vírus; Máscaras higiénicas de proteção contra pós para uso médico; Máscaras higiénicas para prevenção de pó para uso médico; Cintas abdominais [para uso médico]; Corpetes abdominais; Almofadas hipogástricas; Esteiras para terapia de acupressão; Suportes em arco para calçado; Apoios dorsais para fins médicos; Dispositivos para suporte de membros e articulações, para uso médico; Cotoveleiras para epicondolite; Talas para os dedos; Materiais de fixação por talas para uso médico; Compressas sob a forma de vestuário; Sacos de uso médico destinados a manter os instrumentos médicos; Aparelhos de moxibustão; Aparelhos e instrumentos ortopédicos para diagnóstico e uso terapêutico; Cintas para fins ortopédicos; Equipamentos ortopédicos; Instrumentos cirúrgicos destinados à cirurgia ortopédica; Sapatos ortopédicos; Ligaduras de suporte ortopédico; Suportes ortopédicos; Acessórios ortóticos para calçado; Dispositivos de fixação espinal posterior para a correção de defeitos nas costas; Membros artificiais [próteses]; Suportes médicos para o corpo; Suportes de pulso para uso médico; Suportes de tornozelo para uso médico; Aparelhos ortopédicos vertebrais; Aparelhos e instrumentos cirúrgicos; Dispositivos e instrumentos médicos para a cirurgia ortopédica; Aparelhos de exercício físico para fins médicos; Ligaduras elásticas.</GoodsServicesDescription>
   <GoodsServicesDescription languageCode="ro">Mănuşi de protecţie de uz medical; Costume chirurgicale sterile; Halate medicale; Halate de uz chirurgical; Halate pentru examinarea pacienţilor; Măşti sanitare de uz medical; Măşti chirurgicale; Măşti de anestezie; Măşti respiratorii de uz medical; Măşti utilizate de personalul medical; Măşti respiratorii, altele decât cele pentru respiraţie artificială; Măşti sanitare de uz medical; Măști sanitare pentru izolarea ciupercilor; Măşti sanitare pentru izolarea germenilor; Măști sanitare pentru izolarea polenului; Măști sanitare pentru izolarea virușilor; Măști sanitare de uz medical pentru izolarea prafului; Măşti sanitare pentru prevenirea prafului, de uz medical; Centuri abdominale [de uz medical]; Corsete abdominale; Comprese abdominale; Covoraşe pentru acupresiune; Suporturi pentru arcada piciorului; Suporturi lombare de uz medical; Proteze pentru membre si incheieturi pentru uz medical; Cotiere pentru epicondilită; Atele pentru degete; Materiale de contenţie de uz medical; Articole de îmbrăcăminte de compresie; Saci medicali pentru păstrarea instrumentelor medicale; Aparate de moxibustie; Aparate şi instrumente ortopedice folosite pentru diagnostic şi terapeutic; Centuri pentru uz ortopedic; Aparate ortopedice; Instrumente chirurgicale folosite în chirurgia ortopedică; Pantofi ortopedici; Bandaje ortopedice de susţinere; Suporturi ortopedice; Inserţii ortopedice pentru încălţăminte; Dispozitive de fixare posterioară a coloanei vertebrale pentru corectarea spatelui; Membre artificiale; Dispozitive medicale pentru susţinerea corpului; Suporturi pentru încheietură de uz medical; Suporturi pentru gleznă de uz medical; Aparate ortopedice pentru coloana vertebrală; Aparate şi instrumente chirurgicale; Dispozitive şi instrumente medicale pentru chirurgia ortopedică; Aparate pentru exerciţii fizice de uz medical; Bandaje elastice.</GoodsServicesDescription>
   <GoodsServicesDescription languageCode="sk">Ochranné rukavice na lekárske účely; Operačné chirurgické odevy; Lekárske nemocničné plášte; Chirurgické odevy; Nemocničné košele na vyšetrovanie pacientov; Sanitárne masky na lekárske účely; Chirurgické masky; Anestéziologické masky; Respiračné masky na lekárske účely; Rúška (pre nemocničný personál); Dýchacie masky na umelé dýchanie; Sanitárne masky na lekárske účely; Hygienické masky na účely izolácie plesní; Sanitárne masky na účely izolovania mikróbov; Hygienické masky na účely izolácie peľu; Hygienické masky na účely izolovania vírusov; Hygienické masky na ochranu pred prachom na lekárske účely; Sanitárne masky na ochranu pred prachom na lekárske účely; Brušné pásy na lekárske účely; Brušné korzety; Podbruškové vatované ochranné vložky; Akupresúrne podložky; Ortopedické vložky do topánok; Lekárske ortézy na chrbát; Výstuhy pre končatiny a kĺby na lekárske účely; Chrániče lakťov používané pri zápale epikondylu; Dlahy na prsty; Dlahové materiály na lekárske použitie; Sťahovacie oblečenie; Lekárske vrecká na odkladanie lekárskych nástrojov; Zariadenia na moxovanie; Ortopedické prístroje a nástroje na diagnostické a terapeutické účely; Ortopedické pásy; Ortopedické prístroje; Chirurgické nástroje používané v ortopedickej chirurgii; Ortopedická obuv; Ortopedické podporné bandáže; Ortopedické podpory; Ortopedické vložky do obuvi; Zariadenia na posteriórnu fixáciu chrbtice na nápravu porúch chrbta; Protézy (umelé končatiny); Lekárske podpory pre telo; Podpery zápästia na lekárske použitie; Členková bandáž na lekárske účely; Chrbticové ortopedické zariadenia; Chirurgické prístroje a nástroje; Lekárske nástroje a zariadenia pre ortopedickú chirurgiu; Telocvičné prístroje na liečebné použitie; Elastické obväzy.</GoodsServicesDescription>
   <GoodsServicesDescription languageCode="sl">Zaščitne rokavice za medicinsko uporabo; Kirurška oblačila za operacije; Medicinske halje; Halje za kirurško uporabo; Halje za pregledovanje pacientov; Higienske maske za medicinske namene; Kirurške maske; Anestezijske maske; Dihalne maske za medicinske namene; Maske za medicinsko osebje; Dihalne maske za umetno dihanje; Higienske maske za medicinsko uporabo; Higienske maske za namen izolacije glivic; Sanitarne maske za namen izolacije mikrobov; Higienske maske za namen izolacije peloda; Sanitarne maske za namen izolacije virusov; Higienske maske za zaščito pred prahom za medicinske namene; Higienske maske za zaščito pred prahom za medicinske namene; Trebušni pasovi za medicinske namene; Trebušni stezniki; Trebušne komprese; Akupresurne blazine; Vložki za obutev; Opore za hrbet za medicinske namene; Oporniki za ude in sklepe za medicinsko uporabo; Ščitniki za komolce za epikondilitis (teniški komolec); Opornice za prste; Imobilizacijski materiali za medicinsko uporabo; Kompresijska oblačila; Medicinske torbe, ki so oblikovane za medicinske instrumente; Aparati za moksibustijo; Ortopedski aparati in instrumenti za diagnostično in terapevtsko uporabo; Pasovi za ortopedske namene; Ortopedske naprave; Kirurški instrumenti, ki se uporabljajo za ortopedsko kirurgijo; Ortopedski čevlji; Ortopedske oporne obveze; Ortopedske podpore; Ortotski vložki za obutev; Naprave za zadnjo fiksacijo hrbtenice za korekcijo napak hrbta; Proteze (umetni udje); Medicinske opore za telo; Opore za zapestje za medicinsko uporabo; Opornice za gležnje, za medicinsko uporabo; Ortopedski aparati za vretence; Kirurški aparati in instrumenti; Medicinske naprave in instrumenti za ortopedsko kirurgijo; Aparati za telesno vadbo za medicinske namene; Elastični povoji.</GoodsServicesDescription>
   <GoodsServicesDescription languageCode="sv">Skyddshandskar för medicinskt bruk; Operationskläder; Läkarrockar; Rockar för kirurgiskt bruk; Rockar för användning vid undersökning av patienter; Sanitetsmasker för medicinska ändamål; Operationsmasker; Narkosmasker; Andningsmasker för medicinska ändamål; Munskydd för medicinsk personal; Andningsmasker för konstgjord andning; Sanitetsmasker för medicinskt bruk; Hygienmasker för svampisolering; Hygienmasker för bakterieisolering; Hygienmasker för pollenisolering; Hygienmasker för virusisolering; Sanitära ansiktsmasker för dammisolering, för medicinska ändamål; Sanitära ansiktsmasker för skydd mot damm, för medicinska ändamål; Maggördlar [för medicinska ändamål]; Bukstödkorsetter; Bråckbandskuddar; Spikmattor; Hålfotsinlägg för fotbeklädnader; Ryggstöd för medicinska ändamål; Stödanordningar för lemmar och leder, för medicinsk användning; Armbågsskydd för epikondylit; Fingerskenor; Spjälkningsmaterial för medicinskt bruk; Kompressionskläder; Medicinska väskor som är utformade för att innehålla medicinska instrument; Apparater för behandling med moxer (rullar av torkade örter); Ortopediska apparater och instrument för diagnostisk och terapeutisk användning; Bälten för ortopediska ändamål; Ortopedianordningar; Kirurgiska instrument för användning vid ortopedkirurgi; Ortopediska skor; Ortopediska stödförband; Ortopediska stöd; Ortopediska inlägg för fotbeklädnader; Anordningar för fixering av bakre ryggraden vid korrigering av missbildningar; Konstgjorda lemmar; Medicinska stöd för kroppen; Handledsstöd för medicinskt bruk; Fotledsstöd för medicinskt bruk; Ortopediska vertebrala apparater; Kirurgiska apparater och instrument; Medicinska anordningar och instrument för ortopedisk kirurgi; Kroppsträningsapparater för medicinska ändamål; Bandage (elastiska).</GoodsServicesDescription>
  </ClassDescription>
 </ClassDescriptionDetails>
</GoodsServices>
</GoodsServicesDetails>
<PublicationDetails>
       <Publication>
        <PublicationIdentifier>2020/103</PublicationIdentifier>
        <PublicationSection>A.1</PublicationSection>
        <PublicationDate>2020-06-03</PublicationDate>
        <PublicationPage>0</PublicationPage>
       </Publication>
       <Publication>
        <PublicationIdentifier>2020/176</PublicationIdentifier>
        <PublicationSection>B.1</PublicationSection>
        <PublicationDate>2020-09-15</PublicationDate>
        <PublicationPage>0</PublicationPage>
       </Publication>
      </PublicationDetails>
<RepresentativeDetails>
<RepresentativeKey>
<Identifier>32203</Identifier>
</RepresentativeKey>
</RepresentativeDetails>
</TradeMark>
</TradeMarkDetails>
</TransactionData>
</TransactionContentDetails>
</TradeMarkTransactionBody>
</Transaction>
